MANIFEST.in
README.md
setup.py
hvdvpdq.egg-info/PKG-INFO
hvdvpdq.egg-info/SOURCES.txt
hvdvpdq.egg-info/dependency_links.txt
hvdvpdq.egg-info/entry_points.txt
hvdvpdq.egg-info/requires.txt
hvdvpdq.egg-info/top_level.txt
pdq/cpp/common/pdqbasetypes.h
pdq/cpp/common/pdqhashtypes.cpp
pdq/cpp/common/pdqhashtypes.h
pdq/cpp/downscaling/downscaling.cpp
pdq/cpp/downscaling/downscaling.h
pdq/cpp/hashing/pdqhashing.cpp
pdq/cpp/hashing/pdqhashing.h
pdq/cpp/hashing/torben.cpp
pdq/cpp/hashing/torben.h
pdq/cpp/io/hashio.cpp
pdq/cpp/io/hashio.h
vpdq/LICENSE.txt
vpdq/setup.py
vpdq/version.txt
vpdq/vpdq-release.py
vpdq/benchmark/benchmark.py
vpdq/cpp/Makefile
vpdq/cpp/regtest.py
vpdq/cpp/vpdq_match.py
vpdq/cpp/bin/match-hashes-brute.cpp
vpdq/cpp/bin/match-hashes-byline.cpp
vpdq/cpp/bin/vpdq-hash-video.cpp
vpdq/cpp/hashing/bufferhasher.cpp
vpdq/cpp/hashing/bufferhasher.h
vpdq/cpp/hashing/filehasher.cpp
vpdq/cpp/hashing/filehasher.h
vpdq/cpp/hashing/matchTwoHash.cpp
vpdq/cpp/hashing/matchTwoHash.h
vpdq/cpp/hashing/vpdqHashType.h
vpdq/cpp/io/vpdqio.cpp
vpdq/cpp/io/vpdqio.h
vpdq/python/README.md
vpdq/python/__init__.py
vpdq/python/vpdq.cpp
vpdq/python/vpdq.pyx
vpdq/python/tests/test_util.py
vpdq/python/tests/test_vpdq_hash.py