Metadata-Version: 2.1
Name: hvdvpdq
Version: 0.0.11
Summary: Python bindings for Facebook VPDQ hash fixed
Home-page: UNKNOWN
Author: Facebook
Author-email: threatexchange@fb.com
License: BSD
Platform: UNKNOWN
